aleph0/__init__.py
aleph0/algs/__init__.py
aleph0/algs/algorithm.py
aleph0/algs/play_game.py
aleph0/algs/learning/__init__.py
aleph0/algs/learning/alephzero.py
aleph0/algs/learning/dqn.py
aleph0/algs/learning/human.py
aleph0/algs/nonlearning/__init__.py
aleph0/algs/nonlearning/exhaust_search.py
aleph0/algs/nonlearning/mcts.py
aleph0/algs/nonlearning/randy.py
aleph0/examples/__init__.py
aleph0/examples/chess/__init__.py
aleph0/examples/chess/game/__init__.py
aleph0/examples/chess/game/board.py
aleph0/examples/chess/game/chess2d.py
aleph0/examples/chess/game/chess5d.py
aleph0/examples/chess/game/chess5d_old.py
aleph0/examples/chess/game/multiverse.py
aleph0/examples/chess/game/piece.py
aleph0/examples/chess/game/timeline.py
aleph0/examples/jenga/__init__.py
aleph0/examples/jenga/game/__init__.py
aleph0/examples/jenga/game/block.py
aleph0/examples/jenga/game/jenga.py
aleph0/examples/tictactoe/__init__.py
aleph0/examples/tictactoe/game/__init__.py
aleph0/examples/tictactoe/game/tictactoe.py
aleph0/examples/tictactoe/game/ultimate.py
aleph0/game/__init__.py
aleph0/game/selection_game.py
aleph0/networks/__init__.py
aleph0/networks/ffn.py
aleph0/networks/architect/__init__.py
aleph0/networks/architect/architect.py
aleph0/networks/architect/beginning/__init__.py
aleph0/networks/architect/beginning/board_embedding.py
aleph0/networks/architect/beginning/input_embedding.py
aleph0/networks/architect/beginning/pos_enc.py
aleph0/networks/architect/end/__init__.py
aleph0/networks/architect/end/policy_value.py
aleph0/networks/architect/middle/__init__.py
aleph0/networks/architect/middle/chainformer.py
aleph0/networks/architect/middle/cnn.py
aleph0/networks/architect/middle/collapse.py
aleph0/networks/architect/middle/former.py
aleph0/networks/architect/middle/transformer.py
aleph0/networks/buffers/__init__.py
aleph0/networks/buffers/buffer.py
aleph0/tests/easy_chess_dqn.py
aleph0-0.0.10000369.dist-info/LICENSE
aleph0-0.0.10000369.dist-info/METADATA
aleph0-0.0.10000369.dist-info/WHEEL
aleph0-0.0.10000369.dist-info/top_level.txt
aleph0-0.0.10000369.dist-info/RECORD
