Metadata-Version: 2.1
Name: aleph0
Version: 0.0.10000369
Summary: alphazero implemented for games with state/action spaces a finite subset of a countable space
Author-email: Pranav <pranavraj575@gmail.com>
Project-URL: Homepage, https://github.com/pranavraj575/aleph0
Classifier: Programming Language :: Python :: 3
Classifier: License :: OSI Approved :: MIT License
Classifier: Operating System :: OS Independent
Requires-Python: >=3.10
License-File: LICENSE
Requires-Dist: torch
Requires-Dist: numpy
Provides-Extra: jenga
Requires-Dist: scipy ; extra == 'jenga'
Requires-Dist: matplotlib ; extra == 'jenga'
